AUTHORS.md
LICENSE
MANIFEST.in
README.md
setup.cfg
setup.py
csvcleaner/__init__.py
csvcleaner/csvcleaner.py
csvcleaner.egg-info/PKG-INFO
csvcleaner.egg-info/SOURCES.txt
csvcleaner.egg-info/dependency_links.txt
csvcleaner.egg-info/not-zip-safe
csvcleaner.egg-info/top_level.txt
csvcleaner/blacklist/LICENSE
csvcleaner/blacklist/en