Metadata-Version: 1.1
Name: csvcleaner
Version: 1.0.6
Summary: Removes rows containing blacklisted words from a CSV file.
Home-page: https://github.com/palmer/csvcleaner
Author: James C. Palmer
Author-email: james@pgmny.com
License: Apache 2.0
Platform: UNKNOWN
Classifier: Development Status :: 4 - Beta
Classifier: Intended Audience :: Developers
Classifier: Natural Language :: English
Classifier: License :: OSI Approved :: Apache Software License
Classifier: Programming Language :: Python
Classifier: Programming Language :: Python :: 2.7
